automat/__init__.py
automat/_core.py
automat/_discover.py
automat/_introspection.py
automat/_methodical.py
automat/_runtimeproto.py
automat/_typed.py
automat/_visualize.py
automat/py.typed
automat/_test/__init__.py
automat/_test/test_core.py
automat/_test/test_discover.py
automat/_test/test_methodical.py
automat/_test/test_trace.py
automat/_test/test_type_based.py
automat/_test/test_visualize.py
Automat-24.8.0.dist-info/LICENSE
Automat-24.8.0.dist-info/METADATA
Automat-24.8.0.dist-info/WHEEL
Automat-24.8.0.dist-info/entry_points.txt
Automat-24.8.0.dist-info/top_level.txt
Automat-24.8.0.dist-info/RECORD
