Metadata-Version: 2.1
Name: Automat
Version: 24.8.0
Summary: Self-service finite-state machines for the programmer on the go.
Author-email: Glyph <code@glyph.im>
License: Copyright (c) 2014
Project-URL: Documentation, https://automat.readthedocs.io/
Project-URL: Source, https://github.com/glyph/automat/
Keywords: fsm,state machine,automata
Classifier: Intended Audience :: Developers
Classifier: License :: OSI Approved :: MIT License
Classifier: Operating System :: OS Independent
Classifier: Programming Language :: Python
Classifier: Programming Language :: Python :: 3
Classifier: Programming Language :: Python :: 3.8
Classifier: Programming Language :: Python :: 3.9
Classifier: Programming Language :: Python :: 3.10
Classifier: Programming Language :: Python :: 3.11
Classifier: Programming Language :: Python :: 3.12
License-File: LICENSE
Requires-Dist: typing_extensions; python_version < "3.10"
Provides-Extra: visualize
Requires-Dist: graphviz>0.5.1; extra == "visualize"
Requires-Dist: Twisted>=16.1.1; extra == "visualize"
